README
setup.py
li_testing/__init__.py
li_testing/data.py
li_testing/liveserver.py
li_testing/selenium_browser.py
li_testing.egg-info/PKG-INFO
li_testing.egg-info/SOURCES.txt
li_testing.egg-info/dependency_links.txt
li_testing.egg-info/pbr.json
li_testing.egg-info/requires.txt
li_testing.egg-info/top_level.txt