Metadata-Version: 1.1
Name: li-testing
Version: 0.3.19
Summary: Package containing stuff usefull for testing purposes.
Home-page: UNKNOWN
Author: Juca Crispim
Author-email: juca@lojaintegrada.com.br
License: UNKNOWN
Platform: UNKNOWN
Classifier: Development Status :: 3 - Alpha
Classifier: Intended Audience :: Developers
Classifier: Natural Language :: English
Classifier: Operating System :: OS Independent
Classifier: Topic :: Software Development :: Testing
Provides: li_testing
